[
  {
    "reg_number": "927625BCS018",
    "first_name": "CHAARUHASAN",
    "last_name": "S",
    "date": "2026-03-24",
    "time": "08:39 AM",
    "status": "Present"
  },
  {
    "reg_number": "927625BCS034",
    "first_name": "DHIVYAN",
    "last_name": "C",
    "date": "2026-03-24",
    "time": "08:39 AM",
    "status": "Present"
  },
  {
    "reg_number": "927625BCS034",
    "first_name": "DHIVYAN",
    "last_name": "C",
    "date": "2026-03-27",
    "time": "02:24 PM",
    "status": "Present"
  },
  {
    "reg_number": "927625BCS018",
    "first_name": "CHAARUHASAN",
    "last_name": "S",
    "date": "2026-04-11",
    "time": "\u2014",
    "status": "Holiday"
  },
  {
    "reg_number": "927625BCS034",
    "first_name": "DHIVYAN",
    "last_name": "C",
    "date": "2026-04-11",
    "time": "\u2014",
    "status": "Holiday"
  },
  {
    "reg_number": "927625BCS156",
    "first_name": "SREE GANESH",
    "last_name": "M",
    "date": "2026-04-11",
    "time": "\u2014",
    "status": "Holiday"
  },
  {
    "reg_number": "927625BCS034",
    "first_name": "DHIVYAN",
    "last_name": "C",
    "date": "2026-04-13",
    "time": "06:55 PM",
    "status": "Present"
  },
  {
    "reg_number": "927625BCS018",
    "first_name": "CHAARUHASAN",
    "last_name": "S",
    "date": "2026-04-19",
    "time": "\u2014",
    "status": "Holiday"
  },
  {
    "reg_number": "927625BCS034",
    "first_name": "DHIVYAN",
    "last_name": "C",
    "date": "2026-04-19",
    "time": "\u2014",
    "status": "Holiday"
  },
  {
    "reg_number": "927625BCS156",
    "first_name": "SREE GANESH",
    "last_name": "M",
    "date": "2026-04-19",
    "time": "\u2014",
    "status": "Holiday"
  },
  {
    "reg_number": "927625BCS156",
    "first_name": "SREE GANESH",
    "last_name": "M",
    "date": "2026-03-24",
    "time": "08:10 AM",
    "status": "Present"
  },
  {
    "reg_number": "927625BCS018",
    "first_name": "CHAARUHASAN",
    "last_name": "S",
    "date": "2026-04-20",
    "time": "08:23 PM",
    "status": "Present"
  },
  {
    "reg_number": "927625BCS034",
    "first_name": "DHIVYAN",
    "last_name": "C",
    "date": "2026-04-20",
    "time": "08:23 PM",
    "status": "Present"
  },
  {
    "reg_number": "927625BCS156",
    "first_name": "SREE GANESH",
    "last_name": "M",
    "date": "2026-04-20",
    "time": "08:23 PM",
    "status": "Present"
  },
  {
    "reg_number": "927625BCS034",
    "first_name": "DHIVYAN",
    "last_name": "C",
    "date": "2026-05-10",
    "time": "06:22 PM",
    "status": "Present"
  },
  {
    "reg_number": "927625BCS034",
    "first_name": "DHIVYAN",
    "last_name": "C",
    "date": "2026-05-18",
    "time": "06:28 AM",
    "status": "Present"
  },
  {
    "reg_number": "927625BCS034",
    "first_name": "DHIVYAN",
    "last_name": "C",
    "date": "2026-05-31",
    "time": "07:13 PM",
    "status": "Present"
  },
  {
    "reg_number": "927625BCS034",
    "first_name": "DHIVYAN",
    "last_name": "C",
    "date": "2026-06-01",
    "time": "08:35 AM",
    "status": "Present"
  },
  {
    "reg_number": "927625BCS034",
    "first_name": "DHIVYAN",
    "last_name": "C",
    "date": "2026-06-03",
    "time": "05:06 PM",
    "status": "Present"
  },
  {
    "reg_number": "927625BCS034",
    "first_name": "DHIVYAN",
    "last_name": "C",
    "date": "2026-06-04",
    "time": "06:36 AM",
    "status": "Present"
  },
  {
    "reg_number": "927625BCS018",
    "first_name": "CHAARUHASAN",
    "last_name": "S",
    "date": "2026-06-04",
    "time": "12:29 PM",
    "status": "Present"
  },
  {
    "reg_number": "927625BCS034",
    "first_name": "DHIVYAN",
    "last_name": "C",
    "date": "2026-06-18",
    "time": "04:53 PM",
    "status": "Present"
  },
  {
    "reg_number": "927625BCS034",
    "first_name": "DHIVYAN",
    "last_name": "C",
    "date": "2026-06-23",
    "time": "04:38 PM",
    "status": "Present"
  },
  {
    "reg_number": "927625BCS034",
    "first_name": "DHIVYAN",
    "last_name": "C",
    "date": "2026-06-27",
    "time": "09:31 AM",
    "status": "Present"
  },
  {
    "reg_number": "927625BCS034",
    "first_name": "DHIVYAN",
    "last_name": "C",
    "date": "2026-07-11",
    "time": "07:06 PM",
    "status": "Present"
  }
]